django_rest_test-0.8.1b0.dist-info/DESCRIPTION.rst
django_rest_test-0.8.1b0.dist-info/METADATA
django_rest_test-0.8.1b0.dist-info/RECORD
django_rest_test-0.8.1b0.dist-info/WHEEL
django_rest_test-0.8.1b0.dist-info/metadata.json
django_rest_test-0.8.1b0.dist-info/top_level.txt
rest_test/__init__.py
rest_tests/__init__.py
tests/__init__.py
tests/manage.py
tests/test_basic.py
tests/test_decorators.py
tests/project/__init__.py
tests/project/settings.py
tests/project/urls.py
tests/project/wsgi.py
