Metadata-Version: 2.0
Name: django-rest-test
Version: 0.8.1b0
Summary: Semi-automated testing for Django REST framework API
Home-page: http://github.com/baseclue/django-rest-test
Author: Jan Češpivo
Author-email: jan.cespivo@gmail.com
License: Apache 2.0
Platform: UNKNOWN
Requires-Dist: djangorestframework
